tms_django_config/__init__.py
tms_django_config/admin.py
tms_django_config/apps.py
tms_django_config/models.py
tms_django_config/migrations/0001_initial.py
tms_django_config/migrations/__init__.py
tms_django_config-1.0.0.dist-info/METADATA
tms_django_config-1.0.0.dist-info/WHEEL
tms_django_config-1.0.0.dist-info/top_level.txt
tms_django_config-1.0.0.dist-info/RECORD
