Metadata-Version: 2.1
Name: tms-django-config
Version: 1.0.0
Summary: Simple config table with admin management
Home-page: https://github.com/tms-software/django-config
Author: Franck COUTOULY
Author-email: franck.coutouly@tms-software.ch
Classifier: Programming Language :: Python :: 3
Classifier: License :: OSI Approved :: MIT License
Classifier: Operating System :: OS Independent
Requires-Python: >=3.6, <4
Requires-Dist: django
Requires-Dist: django-admin
